LICENSE
MANIFEST.in
README.md
setup.py
test_travis_pypi/__init__.py
test_travis_pypi/__version__.py
test_travis_pypi/core.py
test_travis_pypi.egg-info/PKG-INFO
test_travis_pypi.egg-info/SOURCES.txt
test_travis_pypi.egg-info/dependency_links.txt
test_travis_pypi.egg-info/top_level.txt